telegram_notify/.ruff_cache/.gitignore
telegram_notify/.ruff_cache/0.12.7/12615113371061312032
telegram_notify/.ruff_cache/CACHEDIR.TAG
telegram_notify/__init__.py
telegram_notify/notify.py
telegram_notify/record.py
telegram_notify-0.1.0.dist-info/WHEEL
telegram_notify-0.1.0.dist-info/entry_points.txt
telegram_notify-0.1.0.dist-info/METADATA
telegram_notify-0.1.0.dist-info/RECORD
