Metadata-Version: 2.3
Name: telegram-notify
Version: 0.1.0
Summary: Add your description here
Author: angusforrest
Author-email: angusforrest <contact@angusforrest.com>
Requires-Dist: requests>=2.32.4
Requires-Python: >=3.12
